tame/__init__.py
tame/__main__.py
tame-0.0.1.dist-info/LICENSE
tame-0.0.1.dist-info/METADATA
tame-0.0.1.dist-info/WHEEL
tame-0.0.1.dist-info/top_level.txt
tame-0.0.1.dist-info/RECORD
