Metadata-Version: 2.1
Name: tame
Version: 0.0.1
Summary: A minimal YAML-based metadata management system.
Home-page: https://github.com/meson800/tame
Author: Christopher Johnstone
Author-email: meson800@gmail.com
License: MIT
Platform: UNKNOWN
Classifier: Development Status :: 2 - Pre-Alpha
Classifier: Programming Language :: Python :: 3
Classifier: License :: OSI Approved :: MIT License
Classifier: Operating System :: OS Independent
Requires-Python: >=3
Requires-Dist: PyYAML
